doubao_image_gen.py
doubao_mcp_server.py
doubao_image_mcp_server-1.0.1.dist-info/METADATA
doubao_image_mcp_server-1.0.1.dist-info/WHEEL
doubao_image_mcp_server-1.0.1.dist-info/entry_points.txt
doubao_image_mcp_server-1.0.1.dist-info/licenses/LICENSE
doubao_image_mcp_server-1.0.1.dist-info/RECORD
