Metadata-Version: 2.4
Name: doubao_image_mcp_server
Version: 1.0.1
Summary: Image generation MCP server based on Doubao API
Project-URL: Homepage, https://github.com/suibin521/doubao-image-mcp-server
Project-URL: Repository, https://github.com/suibin521/doubao-image-mcp-server
Project-URL: Bug Tracker, https://github.com/suibin521/doubao-image-mcp-server/issues
Project-URL: Documentation, https://github.com/suibin521/doubao-image-mcp-server#readme
Author-email: suibin521 <your-email@example.com>
License-File: LICENSE
Classifier: Development Status :: 5 - Production/Stable
Classifier: Intended Audience :: Developers
Classifier: License :: OSI Approved :: MIT License
Classifier: Programming Language :: Python :: 3
Classifier: Programming Language :: Python :: 3.13
Classifier: Topic :: Multimedia :: Graphics
Classifier: Topic :: Scientific/Engineering :: Artificial Intelligence
Classifier: Topic :: Software Development :: Libraries :: Python Modules
Requires-Python: >=3.13
Requires-Dist: fastmcp>=0.2.0
Requires-Dist: mcp>=1.0.0
Requires-Dist: pillow>=10.0.0
Requires-Dist: requests>=2.31.0
Requires-Dist: volcengine-python-sdk[ark]>=1.0.0
